[
    {
        "volume": "1675960",
        "average": "1.05",
        "high": "1.29",
        "low": "0.819198",
        "marketcap": "",
        "date": "20180110",
        "close": "1.10",
        "open": "1.29"
    },
    {
        "volume": "1576130",
        "average": "1.44",
        "high": "1.61",
        "low": "1.27",
        "marketcap": "",
        "date": "20180109",
        "close": "1.29",
        "open": "1.55"
    },
    {
        "volume": "3554120",
        "average": "1.64",
        "high": "1.98",
        "low": "1.29",
        "marketcap": "",
        "date": "20180108",
        "close": "1.43",
        "open": "1.40"
    },
    {
        "volume": "2503520",
        "average": "1.37",
        "high": "1.93",
        "low": "0.817000",
        "marketcap": "",
        "date": "20180107",
        "close": "1.37",
        "open": "0.880122"
    },
    {
        "volume": "1289000",
        "average": "0.86",
        "high": "1.06",
        "low": "0.655172",
        "marketcap": "",
        "date": "20180106",
        "close": "0.885787",
        "open": "0.792919"
    },
    {
        "volume": "1067910",
        "average": "0.73",
        "high": "0.826903",
        "low": "0.624644",
        "marketcap": "",
        "date": "20180105",
        "close": "0.792547",
        "open": "0.708323"
    },
    {
        "volume": "1649650",
        "average": "0.63",
        "high": "0.765948",
        "low": "0.499885",
        "marketcap": "",
        "date": "20180104",
        "close": "0.708329",
        "open": "0.580546"
    },
    {
        "volume": "1365470",
        "average": "0.54",
        "high": "0.644735",
        "low": "0.442563",
        "marketcap": "",
        "date": "20180103",
        "close": "0.581481",
        "open": "0.442563"
    },
    {
        "volume": "533391",
        "average": "0.46",
        "high": "0.498570",
        "low": "0.425049",
        "marketcap": "",
        "date": "20180102",
        "close": "0.442971",
        "open": "0.432039"
    },
    {
        "volume": "187550",
        "average": "0.44",
        "high": "0.475417",
        "low": "0.403799",
        "marketcap": "",
        "date": "20180101",
        "close": "0.433888",
        "open": "0.475417"
    },
    {
        "volume": "178425",
        "average": "0.43",
        "high": "0.478297",
        "low": "0.378944",
        "marketcap": "",
        "date": "20171231",
        "close": "0.474583",
        "open": "0.419898"
    },
    {
        "volume": "113788",
        "average": "0.45",
        "high": "0.509405",
        "low": "0.380669",
        "marketcap": "",
        "date": "20171230",
        "close": "0.423410",
        "open": "0.498014"
    },
    {
        "volume": "60442",
        "average": "0.47",
        "high": "0.515814",
        "low": "0.429462",
        "marketcap": "",
        "date": "20171229",
        "close": "0.498706",
        "open": "0.476330"
    },
    {
        "volume": "49234",
        "average": "0.44",
        "high": "0.507956",
        "low": "0.369992",
        "marketcap": "",
        "date": "20171228",
        "close": "0.473596",
        "open": "0.452102"
    }
]