[
    {
        "volume": "22516400",
        "average": "227.06",
        "high": "239.41",
        "low": "214.72",
        "marketcap": "3141730000",
        "date": "20150205",
        "close": "217.11",
        "coin": "bitcoin",
        "open": "227.66"
    },
    {
        "volume": "1221720",
        "average": "0.01",
        "high": "0.014472",
        "low": "0.013503",
        "marketcap": "418285000",
        "date": "20150205",
        "close": "0.014466",
        "coin": "ripple",
        "open": "0.013503"
    },
    {
        "volume": "4490700",
        "average": "1.77",
        "high": "1.81",
        "low": "1.73",
        "marketcap": "64942100",
        "date": "20150205",
        "close": "1.74",
        "coin": "litecoin",
        "open": "1.79"
    },
    {
        "volume": "48565",
        "average": "0.00",
        "high": "0.004024",
        "low": "0.003605",
        "marketcap": "13530400",
        "date": "20150205",
        "close": "0.004001",
        "coin": "stellar",
        "open": "0.003765"
    },
    {
        "volume": "49522",
        "average": "1.81",
        "high": "1.89",
        "low": "1.73",
        "marketcap": "9349800",
        "date": "20150205",
        "close": "1.77",
        "coin": "dash",
        "open": "1.83"
    },
    {
        "volume": "13746",
        "average": "0.28",
        "high": "0.298088",
        "low": "0.266988",
        "marketcap": "1761170",
        "date": "20150205",
        "close": "0.272273",
        "coin": "monero",
        "open": "0.289486"
    },
    {
        "volume": "45",
        "average": "0.00",
        "high": "0.000005",
        "low": "0.000002",
        "marketcap": "15181",
        "date": "20150205",
        "close": "0.000003",
        "coin": "verge",
        "open": "0.000002"
    },
    {
        "volume": "4408",
        "average": "0.00",
        "high": "0.000012",
        "low": "0.000011",
        "marketcap": "1950790",
        "date": "20150205",
        "close": "0.000011",
        "coin": "bytecoin-bcn",
        "open": "0.000012"
    },
    {
        "volume": "95648",
        "average": "0.01",
        "high": "0.010396",
        "low": "0.009968",
        "marketcap": "25897700",
        "date": "20150205",
        "close": "0.010066",
        "coin": "bitshares",
        "open": "0.010367"
    },
    {
        "volume": "153575",
        "average": "0.00",
        "high": "0.000152",
        "low": "0.000140",
        "marketcap": "14411200",
        "date": "20150205",
        "close": "0.000142",
        "coin": "dogecoin",
        "open": "0.000147"
    },
    {
        "volume": "19047",
        "average": "0.00",
        "high": "0.000158",
        "low": "0.000103",
        "marketcap": "372240",
        "date": "20150205",
        "close": "0.000147",
        "coin": "digibyte",
        "open": "0.000107"
    },
    {
        "volume": "619",
        "average": "0.00",
        "high": "0.001713",
        "low": "0.001192",
        "marketcap": "",
        "date": "20150205",
        "close": "0.001303",
        "coin": "nexus",
        "open": "0.001523"
    },
    {
        "volume": "1822",
        "average": "0.00",
        "high": "0.000025",
        "low": "0.000020",
        "marketcap": "564560",
        "date": "20150205",
        "close": "0.000022",
        "coin": "reddcoin",
        "open": "0.000021"
    },
    {
        "volume": "2097",
        "average": "0.05",
        "high": "0.051265",
        "low": "0.046625",
        "marketcap": "828155",
        "date": "20150205",
        "close": "0.048911",
        "coin": "monacoin",
        "open": "0.050842"
    },
    {
        "volume": "10296",
        "average": "0.00",
        "high": "0.000078",
        "low": "0.000067",
        "marketcap": "486147",
        "date": "20150205",
        "close": "0.000072",
        "coin": "digitalnote",
        "open": "0.000071"
    },
    {
        "volume": "22341",
        "average": "0.01",
        "high": "0.012029",
        "low": "0.010954",
        "marketcap": "11534200",
        "date": "20150205",
        "close": "0.011067",
        "coin": "nxt",
        "open": "0.011534"
    },
    {
        "volume": "6530",
        "average": "0.93",
        "high": "0.989498",
        "low": "0.864133",
        "marketcap": "1167460",
        "date": "20150205",
        "close": "0.866562",
        "coin": "bitcoindark",
        "open": "0.971151"
    },
    {
        "volume": "7460",
        "average": "0.03",
        "high": "0.032096",
        "low": "0.028237",
        "marketcap": "14478500",
        "date": "20150205",
        "close": "0.028243",
        "coin": "maidsafecoin",
        "open": "0.031993"
    },
    {
        "volume": "1468",
        "average": "0.00",
        "high": "0.000389",
        "low": "0.000295",
        "marketcap": "154878",
        "date": "20150205",
        "close": "0.000334",
        "coin": "syscoin",
        "open": "0.000388"
    },
    {
        "volume": "675",
        "average": "0.00",
        "high": "0.001222",
        "low": "0.001052",
        "marketcap": "50257",
        "date": "20150205",
        "close": "0.001085",
        "coin": "gamecredits",
        "open": "0.001135"
    },
    {
        "volume": "5797",
        "average": "0.02",
        "high": "0.020067",
        "low": "0.015126",
        "marketcap": "240331",
        "date": "20150205",
        "close": "0.015761",
        "coin": "vertcoin",
        "open": "0.020064"
    },
    {
        "volume": "111",
        "average": "0.03",
        "high": "0.031201",
        "low": "0.025522",
        "marketcap": "270335",
        "date": "20150205",
        "close": "0.025709",
        "coin": "blocknet",
        "open": "0.027007"
    },
    {
        "volume": "609",
        "average": "0.00",
        "high": "0.000135",
        "low": "0.000116",
        "marketcap": "125162",
        "date": "20150205",
        "close": "0.000123",
        "coin": "bitbay",
        "open": "0.000125"
    },
    {
        "volume": "18",
        "average": "0.01",
        "high": "0.006308",
        "low": "0.005381",
        "marketcap": "20869",
        "date": "20150205",
        "close": "0.005987",
        "coin": "ubiq",
        "open": "0.006254"
    },
    {
        "volume": "5388",
        "average": "0.01",
        "high": "0.007263",
        "low": "0.005598",
        "marketcap": "390009",
        "date": "20150205",
        "close": "0.006085",
        "coin": "nav-coin",
        "open": "0.006736"
    },
    {
        "volume": "95",
        "average": "0.01",
        "high": "0.010063",
        "low": "0.009029",
        "marketcap": "325677",
        "date": "20150205",
        "close": "0.009330",
        "coin": "emercoin",
        "open": "0.009509"
    },
    {
        "volume": "62",
        "average": "0.00",
        "high": "0.000271",
        "low": "0.000238",
        "marketcap": "42292",
        "date": "20150205",
        "close": "0.000242",
        "coin": "einsteinium",
        "open": "0.000256"
    },
    {
        "volume": "14354",
        "average": "0.00",
        "high": "0.000595",
        "low": "0.000464",
        "marketcap": "266013",
        "date": "20150205",
        "close": "0.000536",
        "coin": "burst",
        "open": "0.000473"
    },
    {
        "volume": "530",
        "average": "0.02",
        "high": "0.022809",
        "low": "0.020580",
        "marketcap": "280951",
        "date": "20150205",
        "close": "0.021400",
        "coin": "viacoin",
        "open": "0.021335"
    },
    {
        "volume": "33231",
        "average": "0.33",
        "high": "0.344617",
        "low": "0.318690",
        "marketcap": "7339390",
        "date": "20150205",
        "close": "0.319849",
        "coin": "peercoin",
        "open": "0.332732"
    },
    {
        "volume": "83766",
        "average": "1.36",
        "high": "1.62",
        "low": "1.10",
        "marketcap": "4282810",
        "date": "20150205",
        "close": "1.19",
        "coin": "counterparty",
        "open": "1.62"
    },
    {
        "volume": "17",
        "average": "0.00",
        "high": "0.000048",
        "low": "0.000045",
        "marketcap": "6848",
        "date": "20150205",
        "close": "0.000046",
        "coin": "hempcoin",
        "open": "0.000045"
    },
    {
        "volume": "268",
        "average": "0.00",
        "high": "5.9e-07",
        "low": "5.2e-07",
        "marketcap": "111093",
        "date": "20150205",
        "close": "5.7e-07",
        "coin": "mooncoin",
        "open": "5.6e-07"
    },
    {
        "volume": "2",
        "average": "0.01",
        "high": "0.009321",
        "low": "0.007614",
        "marketcap": "40525",
        "date": "20150205",
        "close": "0.007985",
        "coin": "cloakcoin",
        "open": "0.008904"
    },
    {
        "volume": "1109",
        "average": "3.49",
        "high": "3.73",
        "low": "3.24",
        "marketcap": "329878",
        "date": "20150205",
        "close": "3.32",
        "coin": "jinn",
        "open": "3.30"
    },
    {
        "volume": "73",
        "average": "0.00",
        "high": "0.000270",
        "low": "0.000188",
        "marketcap": "10563",
        "date": "20150205",
        "close": "0.000189",
        "coin": "groestlcoin",
        "open": "0.000192"
    },
    {
        "volume": "1273",
        "average": "0.00",
        "high": "0.001630",
        "low": "0.001311",
        "marketcap": "310645",
        "date": "20150205",
        "close": "0.001512",
        "coin": "gulden",
        "open": "0.001485"
    },
    {
        "volume": "1005",
        "average": "0.00",
        "high": "0.004125",
        "low": "0.003686",
        "marketcap": "273049",
        "date": "20150205",
        "close": "0.003759",
        "coin": "feathercoin",
        "open": "0.003886"
    },
    {
        "volume": "2078",
        "average": "2.60",
        "high": "2.77",
        "low": "2.43",
        "marketcap": "2166220",
        "date": "20150205",
        "close": "2.59",
        "coin": "supernet-unity",
        "open": "2.65"
    },
    {
        "volume": "260",
        "average": "0.00",
        "high": "0.003906",
        "low": "0.002925",
        "marketcap": "58595",
        "date": "20150205",
        "close": "0.003561",
        "coin": "iocoin",
        "open": "0.003629"
    },
    {
        "volume": "8978",
        "average": "0.48",
        "high": "0.509498",
        "low": "0.459253",
        "marketcap": "5265350",
        "date": "20150205",
        "close": "0.470386",
        "coin": "namecoin",
        "open": "0.485863"
    },
    {
        "volume": "12",
        "average": "0.00",
        "high": "9.5e-07",
        "low": "8.7e-07",
        "marketcap": "14918",
        "date": "20150205",
        "close": "9.2e-07",
        "coin": "eccoin",
        "open": "8.8e-07"
    },
    {
        "volume": "1251",
        "average": "0.00",
        "high": "0.001420",
        "low": "0.001190",
        "marketcap": "250103",
        "date": "20150205",
        "close": "0.001207",
        "coin": "potcoin",
        "open": "0.001374"
    },
    {
        "volume": "12",
        "average": "0.00",
        "high": "2e-07",
        "low": "8.4e-08",
        "marketcap": "19013",
        "date": "20150205",
        "close": "1.1e-07",
        "coin": "newyorkcoin",
        "open": "2e-07"
    },
    {
        "volume": "6161",
        "average": "0.16",
        "high": "0.163817",
        "low": "0.153181",
        "marketcap": "128346",
        "date": "20150205",
        "close": "0.154678",
        "coin": "bitcny",
        "open": "0.163657"
    },
    {
        "volume": "47",
        "average": "0.00",
        "high": "0.004296",
        "low": "0.003854",
        "marketcap": "140745",
        "date": "20150205",
        "close": "0.003949",
        "coin": "solarcoin",
        "open": "0.004188"
    },
    {
        "volume": "35",
        "average": "0.00",
        "high": "7.2e-08",
        "low": "6.9e-08",
        "marketcap": "21507",
        "date": "20150205",
        "close": "7e-08",
        "coin": "dimecoin",
        "open": "7.2e-08"
    },
    {
        "volume": "197",
        "average": "0.12",
        "high": "0.122656",
        "low": "0.108110",
        "marketcap": "101234",
        "date": "20150205",
        "close": "0.112559",
        "coin": "diamond",
        "open": "0.118162"
    },
    {
        "volume": "6270",
        "average": "0.02",
        "high": "0.019912",
        "low": "0.017958",
        "marketcap": "1417390",
        "date": "20150205",
        "close": "0.018181",
        "coin": "blackcoin",
        "open": "0.018954"
    },
    {
        "volume": "240",
        "average": "0.00",
        "high": "0.000065",
        "low": "0.000059",
        "marketcap": "59351",
        "date": "20150205",
        "close": "0.000060",
        "coin": "myriad",
        "open": "0.000061"
    },
    {
        "volume": "14",
        "average": "0.01",
        "high": "0.005983",
        "low": "0.005145",
        "marketcap": "290836",
        "date": "20150205",
        "close": "0.005199",
        "coin": "faircoin",
        "open": "0.005659"
    },
    {
        "volume": "2720",
        "average": "0.01",
        "high": "0.007190",
        "low": "0.006242",
        "marketcap": "4190410",
        "date": "20150205",
        "close": "0.006441",
        "coin": "nushares",
        "open": "0.006888"
    },
    {
        "volume": "2",
        "average": "0.00",
        "high": "0.000004",
        "low": "0.000003",
        "marketcap": "54575",
        "date": "20150205",
        "close": "0.000003",
        "coin": "mintcoin",
        "open": "0.000003"
    },
    {
        "volume": "599",
        "average": "2.79",
        "high": "3.17",
        "low": "2.42",
        "marketcap": "1687050",
        "date": "20150205",
        "close": "2.42",
        "coin": "omni",
        "open": "3.14"
    },
    {
        "volume": "2",
        "average": "0.00",
        "high": "0.000031",
        "low": "0.000021",
        "marketcap": "1401",
        "date": "20150205",
        "close": "0.000030",
        "coin": "monetaryunit",
        "open": "0.000029"
    },
    {
        "volume": "136",
        "average": "0.00",
        "high": "0.000128",
        "low": "0.000109",
        "marketcap": "37636",
        "date": "20150205",
        "close": "0.000109",
        "coin": "whitecoin",
        "open": "0.000124"
    },
    {
        "volume": "35",
        "average": "0.00",
        "high": "0.004238",
        "low": "0.003687",
        "marketcap": "14889",
        "date": "20150205",
        "close": "0.003725",
        "coin": "neoscoin",
        "open": "0.003865"
    },
    {
        "volume": "34",
        "average": "0.00",
        "high": "0.000009",
        "low": "0.000007",
        "marketcap": "45561",
        "date": "20150205",
        "close": "0.000007",
        "coin": "earthcoin",
        "open": "0.000007"
    },
    {
        "volume": "28",
        "average": "0.00",
        "high": "0.000179",
        "low": "0.000124",
        "marketcap": "5743",
        "date": "20150205",
        "close": "0.000178",
        "coin": "okcash",
        "open": "0.000149"
    },
    {
        "volume": "29",
        "average": "0.00",
        "high": "1.6e-07",
        "low": "1.4e-07",
        "marketcap": "40282",
        "date": "20150205",
        "close": "1.5e-07",
        "coin": "fedoracoin",
        "open": "1.4e-07"
    },
    {
        "volume": "3030",
        "average": "0.00",
        "high": "0.000348",
        "low": "0.000242",
        "marketcap": "38646",
        "date": "20150205",
        "close": "0.000313",
        "coin": "foldingcoin",
        "open": "0.000348"
    },
    {
        "volume": "0",
        "average": "0.00",
        "high": "0.001132",
        "low": "0.001016",
        "marketcap": "23549",
        "date": "20150205",
        "close": "0.001029",
        "coin": "rubycoin",
        "open": "0.001071"
    },
    {
        "volume": "8467",
        "average": "0.01",
        "high": "0.010165",
        "low": "0.007424",
        "marketcap": "230240",
        "date": "20150205",
        "close": "0.008210",
        "coin": "vericoin",
        "open": "0.008538"
    },
    {
        "volume": "24",
        "average": "0.00",
        "high": "0.000153",
        "low": "0.000130",
        "marketcap": "49398",
        "date": "20150205",
        "close": "0.000137",
        "coin": "pinkcoin",
        "open": "0.000136"
    },
    {
        "volume": "1741",
        "average": "0.00",
        "high": "0.000493",
        "low": "0.000377",
        "marketcap": "192196",
        "date": "20150205",
        "close": "0.000466",
        "coin": "circuits-of-value",
        "open": "0.000480"
    },
    {
        "volume": "7",
        "average": "0.00",
        "high": "0.000150",
        "low": "0.000123",
        "marketcap": "10827",
        "date": "20150205",
        "close": "0.000124",
        "coin": "florincoin",
        "open": "0.000129"
    },
    {
        "volume": "7668",
        "average": "1.63",
        "high": "1.79",
        "low": "1.47",
        "marketcap": "790031",
        "date": "20150205",
        "close": "1.56",
        "coin": "clams",
        "open": "1.55"
    },
    {
        "volume": "4943",
        "average": "0.01",
        "high": "0.007181",
        "low": "0.005588",
        "marketcap": "139829",
        "date": "20150205",
        "close": "0.005699",
        "coin": "stealthcoin",
        "open": "0.006489"
    },
    {
        "volume": "275",
        "average": "0.00",
        "high": "0.000015",
        "low": "0.000012",
        "marketcap": "27430",
        "date": "20150205",
        "close": "0.000012",
        "coin": "noblecoin",
        "open": "0.000013"
    },
    {
        "volume": "82",
        "average": "0.00",
        "high": "0.000100",
        "low": "0.000063",
        "marketcap": "8256",
        "date": "20150205",
        "close": "0.000078",
        "coin": "energycoin",
        "open": "0.000072"
    },
    {
        "volume": "1",
        "average": "0.00",
        "high": "0.000002",
        "low": "0.000002",
        "marketcap": "34166",
        "date": "20150205",
        "close": "0.000002",
        "coin": "carboncoin",
        "open": "0.000002"
    },
    {
        "volume": "101",
        "average": "0.00",
        "high": "0.000004",
        "low": "0.000003",
        "marketcap": "109588",
        "date": "20150205",
        "close": "0.000004",
        "coin": "zeitcoin",
        "open": "0.000004"
    },
    {
        "volume": "234",
        "average": "0.00",
        "high": "0.000009",
        "low": "0.000004",
        "marketcap": "202664",
        "date": "20150205",
        "close": "0.000004",
        "coin": "pandacoin-pnd",
        "open": "0.000006"
    },
    {
        "volume": "9",
        "average": "0.00",
        "high": "0.000892",
        "low": "0.000674",
        "marketcap": "3041",
        "date": "20150205",
        "close": "0.000861",
        "coin": "bitsend",
        "open": "0.000675"
    },
    {
        "volume": "3614",
        "average": "0.07",
        "high": "0.074533",
        "low": "0.057366",
        "marketcap": "122145",
        "date": "20150205",
        "close": "0.060751",
        "coin": "spreadcoin",
        "open": "0.069040"
    },
    {
        "volume": "67",
        "average": "0.00",
        "high": "0.000090",
        "low": "0.000076",
        "marketcap": "36332",
        "date": "20150205",
        "close": "0.000080",
        "coin": "artbyte",
        "open": "0.000088"
    },
    {
        "volume": "8515",
        "average": "1.00",
        "high": "1.03",
        "low": "0.963576",
        "marketcap": "812322",
        "date": "20150205",
        "close": "0.975846",
        "coin": "bitusd",
        "open": "1.02"
    },
    {
        "volume": "54",
        "average": "0.01",
        "high": "0.010194",
        "low": "0.007023",
        "marketcap": "183140",
        "date": "20150205",
        "close": "0.007062",
        "coin": "curecoin",
        "open": "0.007283"
    },
    {
        "volume": "382",
        "average": "0.05",
        "high": "0.060703",
        "low": "0.042053",
        "marketcap": "46391",
        "date": "20150205",
        "close": "0.042246",
        "coin": "bitmark",
        "open": "0.049873"
    },
    {
        "volume": "2839",
        "average": "0.04",
        "high": "0.038811",
        "low": "0.033780",
        "marketcap": "322616",
        "date": "20150205",
        "close": "0.033850",
        "coin": "primecoin",
        "open": "0.036550"
    },
    {
        "volume": "482",
        "average": "0.02",
        "high": "0.021162",
        "low": "0.018000",
        "marketcap": "59033",
        "date": "20150205",
        "close": "0.018841",
        "coin": "boolberry",
        "open": "0.019711"
    },
    {
        "volume": "85",
        "average": "0.00",
        "high": "0.000183",
        "low": "0.000137",
        "marketcap": "21681",
        "date": "20150205",
        "close": "0.000152",
        "coin": "dopecoin",
        "open": "0.000163"
    },
    {
        "volume": "702",
        "average": "3.04",
        "high": "3.23",
        "low": "2.84",
        "marketcap": "563540",
        "date": "20150205",
        "close": "2.89",
        "coin": "unobtanium",
        "open": "2.91"
    },
    {
        "volume": "898",
        "average": "0.00",
        "high": "0.002472",
        "low": "0.002174",
        "marketcap": "172738",
        "date": "20150205",
        "close": "0.002227",
        "coin": "cannabiscoin",
        "open": "0.002322"
    },
    {
        "volume": "67",
        "average": "0.00",
        "high": "0.000429",
        "low": "0.000328",
        "marketcap": "32439",
        "date": "20150205",
        "close": "0.000349",
        "coin": "pesetacoin",
        "open": "0.000344"
    },
    {
        "volume": "317",
        "average": "0.00",
        "high": "0.000594",
        "low": "0.000468",
        "marketcap": "58743",
        "date": "20150205",
        "close": "0.000501",
        "coin": "hyperstake",
        "open": "0.000560"
    },
    {
        "volume": "10",
        "average": "0.00",
        "high": "0.003858",
        "low": "0.003383",
        "marketcap": "123074",
        "date": "20150205",
        "close": "0.003489",
        "coin": "goldcoin",
        "open": "0.003624"
    },
    {
        "volume": "2",
        "average": "0.12",
        "high": "0.121211",
        "low": "0.113217",
        "marketcap": "6346",
        "date": "20150205",
        "close": "0.113813",
        "coin": "bitcoin-plus",
        "open": "0.114653"
    },
    {
        "volume": "1045",
        "average": "0.01",
        "high": "0.009331",
        "low": "0.007266",
        "marketcap": "93642",
        "date": "20150205",
        "close": "0.008799",
        "coin": "startcoin",
        "open": "0.008215"
    },
    {
        "volume": "3",
        "average": "0.00",
        "high": "0.000029",
        "low": "0.000021",
        "marketcap": "139",
        "date": "20150205",
        "close": "0.000022",
        "coin": "belacoin",
        "open": "0.000023"
    },
    {
        "volume": "40",
        "average": "0.00",
        "high": "0.000250",
        "low": "0.000217",
        "marketcap": "21177",
        "date": "20150205",
        "close": "0.000223",
        "coin": "sexcoin",
        "open": "0.000232"
    },
    {
        "volume": "1148",
        "average": "0.01",
        "high": "0.009949",
        "low": "0.008759",
        "marketcap": "902498",
        "date": "20150205",
        "close": "0.009027",
        "coin": "dnotes",
        "open": "0.009383"
    },
    {
        "volume": "220",
        "average": "0.03",
        "high": "0.032215",
        "low": "0.024004",
        "marketcap": "119043",
        "date": "20150205",
        "close": "0.024114",
        "coin": "blitzcash",
        "open": "0.032136"
    },
    {
        "volume": "344",
        "average": "0.01",
        "high": "0.015237",
        "low": "0.013779",
        "marketcap": "33728",
        "date": "20150205",
        "close": "0.013842",
        "coin": "auroracoin",
        "open": "0.014503"
    },
    {
        "volume": "4",
        "average": "0.00",
        "high": "0.000274",
        "low": "0.000246",
        "marketcap": "60588",
        "date": "20150205",
        "close": "0.000269",
        "coin": "asiacoin",
        "open": "0.000255"
    },
    {
        "volume": "405",
        "average": "0.01",
        "high": "0.005605",
        "low": "0.005098",
        "marketcap": "53127",
        "date": "20150205",
        "close": "0.005276",
        "coin": "riecoin",
        "open": "0.005175"
    },
    {
        "volume": "0",
        "average": "0.01",
        "high": "0.011857",
        "low": "0.009046",
        "marketcap": "20685",
        "date": "20150205",
        "close": "0.009102",
        "coin": "korecoin",
        "open": "0.011762"
    },
    {
        "volume": "1592",
        "average": "0.49",
        "high": "0.514691",
        "low": "0.473785",
        "marketcap": "468600",
        "date": "20150205",
        "close": "0.496678",
        "coin": "novacoin",
        "open": "0.510184"
    },
    {
        "volume": "7618",
        "average": "0.00",
        "high": "0.003531",
        "low": "0.002592",
        "marketcap": "877727",
        "date": "20150205",
        "close": "0.003363",
        "coin": "quark",
        "open": "0.003530"
    },
    {
        "volume": "111",
        "average": "0.00",
        "high": "0.001120",
        "low": "0.000862",
        "marketcap": "",
        "date": "20150205",
        "close": "0.000868",
        "coin": "vtorrent",
        "open": "0.000912"
    },
    {
        "volume": "1759",
        "average": "0.00",
        "high": "0.002865",
        "low": "0.002168",
        "marketcap": "19802",
        "date": "20150205",
        "close": "0.002858",
        "coin": "exclusivecoin",
        "open": "0.002260"
    },
    {
        "volume": "31",
        "average": "0.00",
        "high": "0.000009",
        "low": "0.000006",
        "marketcap": "12526",
        "date": "20150205",
        "close": "0.000007",
        "coin": "ufo-coin",
        "open": "0.000007"
    },
    {
        "volume": "206255",
        "average": "1.02",
        "high": "1.06",
        "low": "0.983455",
        "marketcap": "2236840",
        "date": "20150205",
        "close": "0.999847",
        "coin": "nubits",
        "open": "0.995860"
    },
    {
        "volume": "99",
        "average": "0.00",
        "high": "0.000006",
        "low": "0.000002",
        "marketcap": "2447",
        "date": "20150205",
        "close": "0.000004",
        "coin": "greencoin",
        "open": "0.000005"
    },
    {
        "volume": "10",
        "average": "0.00",
        "high": "4.9e-08",
        "low": "1.9e-08",
        "marketcap": "4307",
        "date": "20150205",
        "close": "3.3e-08",
        "coin": "bunnycoin",
        "open": "4.9e-08"
    },
    {
        "volume": "448",
        "average": "0.02",
        "high": "0.025610",
        "low": "0.021452",
        "marketcap": "534063",
        "date": "20150205",
        "close": "0.022555",
        "coin": "ixcoin",
        "open": "0.025432"
    },
    {
        "volume": "614",
        "average": "0.00",
        "high": "0.000567",
        "low": "0.000470",
        "marketcap": "15874",
        "date": "20150205",
        "close": "0.000523",
        "coin": "trustplus",
        "open": "0.000509"
    },
    {
        "volume": "162",
        "average": "0.01",
        "high": "0.012785",
        "low": "0.011296",
        "marketcap": "24607",
        "date": "20150205",
        "close": "0.011512",
        "coin": "magi",
        "open": "0.012360"
    },
    {
        "volume": "187",
        "average": "0.00",
        "high": "0.003611",
        "low": "0.002801",
        "marketcap": "22356",
        "date": "20150205",
        "close": "0.002866",
        "coin": "terracoin",
        "open": "0.003380"
    },
    {
        "volume": "6",
        "average": "0.00",
        "high": "0.001707",
        "low": "0.001396",
        "marketcap": "6605",
        "date": "20150205",
        "close": "0.001410",
        "coin": "huntercoin",
        "open": "0.001585"
    },
    {
        "volume": "12680",
        "average": "0.14",
        "high": "0.146588",
        "low": "0.137036",
        "marketcap": "221863",
        "date": "20150205",
        "close": "0.141333",
        "coin": "anoncoin",
        "open": "0.140623"
    },
    {
        "volume": "1722",
        "average": "0.00",
        "high": "0.004741",
        "low": "0.004331",
        "marketcap": "346269",
        "date": "20150205",
        "close": "0.004382",
        "coin": "worldcoin",
        "open": "0.004727"
    },
    {
        "volume": "2879",
        "average": "0.00",
        "high": "0.000341",
        "low": "0.000269",
        "marketcap": "173514",
        "date": "20150205",
        "close": "0.000301",
        "coin": "mazacoin",
        "open": "0.000269"
    },
    {
        "volume": "277",
        "average": "0.03",
        "high": "0.030628",
        "low": "0.023325",
        "marketcap": "122764",
        "date": "20150205",
        "close": "0.024190",
        "coin": "bitswift",
        "open": "0.030569"
    },
    {
        "volume": "729",
        "average": "0.00",
        "high": "0.000160",
        "low": "0.000111",
        "marketcap": "88204",
        "date": "20150205",
        "close": "0.000129",
        "coin": "bluecoin",
        "open": "0.000158"
    },
    {
        "volume": "18",
        "average": "0.00",
        "high": "0.000207",
        "low": "0.000186",
        "marketcap": "13419",
        "date": "20150205",
        "close": "0.000189",
        "coin": "cryptonite",
        "open": "0.000203"
    },
    {
        "volume": "21",
        "average": "0.00",
        "high": "0.000647",
        "low": "0.000443",
        "marketcap": "932",
        "date": "20150205",
        "close": "0.000475",
        "coin": "digitalprice",
        "open": "0.000641"
    },
    {
        "volume": "519",
        "average": "0.01",
        "high": "0.009799",
        "low": "0.008250",
        "marketcap": "49524",
        "date": "20150205",
        "close": "0.008326",
        "coin": "e-gulden",
        "open": "0.009255"
    },
    {
        "volume": "1280",
        "average": "0.00",
        "high": "0.000241",
        "low": "0.000211",
        "marketcap": "84380",
        "date": "20150205",
        "close": "0.000224",
        "coin": "netcoin",
        "open": "0.000236"
    },
    {
        "volume": "61",
        "average": "0.00",
        "high": "0.000258",
        "low": "0.000229",
        "marketcap": "56478",
        "date": "20150205",
        "close": "0.000231",
        "coin": "fluttercoin",
        "open": "0.000232"
    },
    {
        "volume": "17",
        "average": "0.00",
        "high": "0.000012",
        "low": "0.000009",
        "marketcap": "112",
        "date": "20150205",
        "close": "0.000009",
        "coin": "canada-ecoin",
        "open": "0.000011"
    },
    {
        "volume": "58",
        "average": "0.05",
        "high": "0.056782",
        "low": "0.047934",
        "marketcap": "49949",
        "date": "20150205",
        "close": "0.051518",
        "coin": "cryptogenic-bullion",
        "open": "0.052239"
    },
    {
        "volume": "11",
        "average": "0.00",
        "high": "0.000208",
        "low": "0.000181",
        "marketcap": "20662",
        "date": "20150205",
        "close": "0.000182",
        "coin": "fastcoin",
        "open": "0.000192"
    },
    {
        "volume": "397",
        "average": "0.10",
        "high": "0.112439",
        "low": "0.091658",
        "marketcap": "35472",
        "date": "20150205",
        "close": "0.092079",
        "coin": "bytecent",
        "open": "0.099372"
    },
    {
        "volume": "398",
        "average": "0.01",
        "high": "0.012854",
        "low": "0.012169",
        "marketcap": "341474",
        "date": "20150205",
        "close": "0.012272",
        "coin": "megacoin",
        "open": "0.012512"
    },
    {
        "volume": "8050",
        "average": "0.05",
        "high": "0.062495",
        "low": "0.044836",
        "marketcap": "101365",
        "date": "20150205",
        "close": "0.055413",
        "coin": "unbreakablecoin",
        "open": "0.046171"
    },
    {
        "volume": "8",
        "average": "0.00",
        "high": "0.000011",
        "low": "0.000009",
        "marketcap": "9989",
        "date": "20150205",
        "close": "0.000009",
        "coin": "tittiecoin",
        "open": "0.000009"
    },
    {
        "volume": "0",
        "average": "0.00",
        "high": "0.000290",
        "low": "0.000260",
        "marketcap": "4243",
        "date": "20150205",
        "close": "0.000271",
        "coin": "smartcoin",
        "open": "0.000269"
    },
    {
        "volume": "36",
        "average": "0.00",
        "high": "0.000505",
        "low": "0.000315",
        "marketcap": "1413",
        "date": "20150205",
        "close": "0.000316",
        "coin": "unitus",
        "open": "0.000324"
    },
    {
        "volume": "44",
        "average": "0.01",
        "high": "0.007182",
        "low": "0.006465",
        "marketcap": "759177",
        "date": "20150205",
        "close": "0.006509",
        "coin": "rimbit",
        "open": "0.006791"
    },
    {
        "volume": "28",
        "average": "0.00",
        "high": "0.000239",
        "low": "0.000121",
        "marketcap": "7492",
        "date": "20150205",
        "close": "0.000217",
        "coin": "petrodollar",
        "open": "0.000122"
    },
    {
        "volume": "1632",
        "average": "0.01",
        "high": "0.007428",
        "low": "0.004981",
        "marketcap": "723616",
        "date": "20150205",
        "close": "0.006381",
        "coin": "fuelcoin",
        "open": "0.007221"
    },
    {
        "volume": "95",
        "average": "0.00",
        "high": "0.001141",
        "low": "0.001043",
        "marketcap": "172855",
        "date": "20150205",
        "close": "0.001049",
        "coin": "zetacoin",
        "open": "0.001069"
    },
    {
        "volume": "62",
        "average": "0.00",
        "high": "0.000429",
        "low": "0.000367",
        "marketcap": "22463",
        "date": "20150205",
        "close": "0.000369",
        "coin": "teslacoin",
        "open": "0.000371"
    },
    {
        "volume": "5",
        "average": "0.00",
        "high": "0.000004",
        "low": "0.000002",
        "marketcap": "9472",
        "date": "20150205",
        "close": "0.000004",
        "coin": "trollcoin",
        "open": "0.000002"
    },
    {
        "volume": "5",
        "average": "0.00",
        "high": "0.000026",
        "low": "0.000024",
        "marketcap": "11799",
        "date": "20150205",
        "close": "0.000024",
        "coin": "piggycoin",
        "open": "0.000025"
    },
    {
        "volume": "1123",
        "average": "0.01",
        "high": "0.007100",
        "low": "0.006393",
        "marketcap": "131154",
        "date": "20150205",
        "close": "0.006458",
        "coin": "digitalcoin",
        "open": "0.006662"
    },
    {
        "volume": "11",
        "average": "0.00",
        "high": "0.005265",
        "low": "0.004724",
        "marketcap": "8237",
        "date": "20150205",
        "close": "0.004773",
        "coin": "fantomcoin",
        "open": "0.004980"
    },
    {
        "volume": "82",
        "average": "0.01",
        "high": "0.008762",
        "low": "0.006646",
        "marketcap": "57174",
        "date": "20150205",
        "close": "0.006960",
        "coin": "hobonickels",
        "open": "0.006965"
    },
    {
        "volume": "234",
        "average": "0.00",
        "high": "0.000136",
        "low": "0.000079",
        "marketcap": "24272",
        "date": "20150205",
        "close": "0.000091",
        "coin": "nyancoin",
        "open": "0.000134"
    },
    {
        "volume": "16",
        "average": "0.02",
        "high": "0.017586",
        "low": "0.015780",
        "marketcap": "343186",
        "date": "20150205",
        "close": "0.015904",
        "coin": "i0coin",
        "open": "0.016559"
    },
    {
        "volume": "7",
        "average": "0.00",
        "high": "0.000002",
        "low": "0.000002",
        "marketcap": "55387",
        "date": "20150205",
        "close": "0.000002",
        "coin": "smileycoin",
        "open": "0.000002"
    },
    {
        "volume": "57",
        "average": "0.11",
        "high": "0.119653",
        "low": "0.107363",
        "marketcap": "5624",
        "date": "20150205",
        "close": "0.108701",
        "coin": "triangles",
        "open": "0.113632"
    },
    {
        "volume": "247",
        "average": "0.01",
        "high": "0.005448",
        "low": "0.004627",
        "marketcap": "133183",
        "date": "20150205",
        "close": "0.004651",
        "coin": "ultracoin",
        "open": "0.005161"
    },
    {
        "volume": "119",
        "average": "0.01",
        "high": "0.005565",
        "low": "0.004778",
        "marketcap": "200588",
        "date": "20150205",
        "close": "0.004780",
        "coin": "maxcoin",
        "open": "0.005119"
    },
    {
        "volume": "33",
        "average": "0.01",
        "high": "0.008925",
        "low": "0.004750",
        "marketcap": "99602",
        "date": "20150205",
        "close": "0.008195",
        "coin": "bitcoin-scrypt",
        "open": "0.008925"
    },
    {
        "volume": "76",
        "average": "0.01",
        "high": "0.007681",
        "low": "0.006699",
        "marketcap": "110995",
        "date": "20150205",
        "close": "0.006722",
        "coin": "deutsche-emark",
        "open": "0.007145"
    },
    {
        "volume": "78",
        "average": "1146.49",
        "high": "1222.18",
        "low": "1070.80",
        "marketcap": "1059",
        "date": "20150205",
        "close": "1160.06",
        "coin": "42-coin",
        "open": "1154.05"
    },
    {
        "volume": "533",
        "average": "0.00",
        "high": "0.000404",
        "low": "0.000327",
        "marketcap": "44107",
        "date": "20150205",
        "close": "0.000356",
        "coin": "aricoin",
        "open": "0.000346"
    },
    {
        "volume": "4",
        "average": "0.64",
        "high": "0.670880",
        "low": "0.601967",
        "marketcap": "10272",
        "date": "20150205",
        "close": "0.608257",
        "coin": "bitbar",
        "open": "0.634582"
    },
    {
        "volume": "82",
        "average": "0.00",
        "high": "0.000707",
        "low": "0.000612",
        "marketcap": "10880",
        "date": "20150205",
        "close": "0.000618",
        "coin": "titcoin",
        "open": "0.000678"
    },
    {
        "volume": "12",
        "average": "0.00",
        "high": "0.000171",
        "low": "0.000142",
        "marketcap": "1734",
        "date": "20150205",
        "close": "0.000143",
        "coin": "britcoin",
        "open": "0.000160"
    },
    {
        "volume": "48",
        "average": "0.00",
        "high": "0.001594",
        "low": "0.001430",
        "marketcap": "25359",
        "date": "20150205",
        "close": "0.001445",
        "coin": "bitstar",
        "open": "0.001489"
    },
    {
        "volume": "815",
        "average": "0.01",
        "high": "0.007519",
        "low": "0.006000",
        "marketcap": "97481",
        "date": "20150205",
        "close": "0.007118",
        "coin": "opal",
        "open": "0.006486"
    },
    {
        "volume": "19",
        "average": "0.00",
        "high": "0.000253",
        "low": "0.000224",
        "marketcap": "6124",
        "date": "20150205",
        "close": "0.000227",
        "coin": "phoenixcoin",
        "open": "0.000231"
    },
    {
        "volume": "2",
        "average": "0.01",
        "high": "0.010905",
        "low": "0.009815",
        "marketcap": "1735",
        "date": "20150205",
        "close": "0.009883",
        "coin": "aurumcoin",
        "open": "0.010311"
    },
    {
        "volume": "111",
        "average": "0.01",
        "high": "0.013975",
        "low": "0.012053",
        "marketcap": "23761",
        "date": "20150205",
        "close": "0.012646",
        "coin": "orbitcoin",
        "open": "0.012757"
    },
    {
        "volume": "59",
        "average": "0.00",
        "high": "0.000215",
        "low": "0.000148",
        "marketcap": "1307",
        "date": "20150205",
        "close": "0.000209",
        "coin": "sooncoin",
        "open": "0.000197"
    },
    {
        "volume": "36",
        "average": "0.01",
        "high": "0.012411",
        "low": "0.009714",
        "marketcap": "53168",
        "date": "20150205",
        "close": "0.009717",
        "coin": "cannacoin",
        "open": "0.011479"
    },
    {
        "volume": "8",
        "average": "0.00",
        "high": "0.000308",
        "low": "0.000254",
        "marketcap": "1202",
        "date": "20150205",
        "close": "0.000264",
        "coin": "redcoin",
        "open": "0.000295"
    },
    {
        "volume": "13",
        "average": "0.00",
        "high": "0.000380",
        "low": "0.000341",
        "marketcap": "6669",
        "date": "20150205",
        "close": "0.000345",
        "coin": "truckcoin",
        "open": "0.000360"
    },
    {
        "volume": "7",
        "average": "0.00",
        "high": "0.000227",
        "low": "0.000204",
        "marketcap": "3447",
        "date": "20150205",
        "close": "0.000208",
        "coin": "joulecoin",
        "open": "0.000220"
    },
    {
        "volume": "103",
        "average": "0.00",
        "high": "0.000358",
        "low": "0.000240",
        "marketcap": "29803",
        "date": "20150205",
        "close": "0.000278",
        "coin": "coin2-1",
        "open": "0.000298"
    },
    {
        "volume": "165444",
        "average": "1.04",
        "high": "1.24",
        "low": "0.831677",
        "marketcap": "13163800",
        "date": "20150205",
        "close": "1.23",
        "coin": "paycoin2",
        "open": "1.03"
    },
    {
        "volume": "148",
        "average": "0.00",
        "high": "0.001012",
        "low": "0.000873",
        "marketcap": "23260",
        "date": "20150205",
        "close": "0.000974",
        "coin": "supercoin",
        "open": "0.001001"
    },
    {
        "volume": "25",
        "average": "0.00",
        "high": "0.001062",
        "low": "0.000756",
        "marketcap": "25368",
        "date": "20150205",
        "close": "0.000831",
        "coin": "gaia",
        "open": "0.001053"
    },
    {
        "volume": "18",
        "average": "0.00",
        "high": "7.1e-08",
        "low": "5.6e-08",
        "marketcap": "5408",
        "date": "20150205",
        "close": "5.7e-08",
        "coin": "dashcoin",
        "open": "6.7e-08"
    },
    {
        "volume": "188",
        "average": "0.02",
        "high": "0.016990",
        "low": "0.013986",
        "marketcap": "37110",
        "date": "20150205",
        "close": "0.014450",
        "coin": "tagcoin",
        "open": "0.016650"
    },
    {
        "volume": "41",
        "average": "0.00",
        "high": "0.005346",
        "low": "0.003268",
        "marketcap": "4066",
        "date": "20150205",
        "close": "0.003511",
        "coin": "bitcoinfast",
        "open": "0.005322"
    },
    {
        "volume": "6",
        "average": "0.00",
        "high": "0.000656",
        "low": "0.000513",
        "marketcap": "1009",
        "date": "20150205",
        "close": "0.000564",
        "coin": "halcyon",
        "open": "0.000620"
    },
    {
        "volume": "122",
        "average": "0.00",
        "high": "0.002677",
        "low": "0.001621",
        "marketcap": "14014",
        "date": "20150205",
        "close": "0.001887",
        "coin": "blakecoin",
        "open": "0.002582"
    },
    {
        "volume": "19",
        "average": "0.00",
        "high": "0.003058",
        "low": "0.002573",
        "marketcap": "12480",
        "date": "20150205",
        "close": "0.002597",
        "coin": "tekcoin",
        "open": "0.002892"
    },
    {
        "volume": "9",
        "average": "0.00",
        "high": "0.000391",
        "low": "0.000090",
        "marketcap": "765",
        "date": "20150205",
        "close": "0.000174",
        "coin": "prime-xi",
        "open": "0.000235"
    },
    {
        "volume": "5",
        "average": "0.00",
        "high": "0.000433",
        "low": "0.000387",
        "marketcap": "4751",
        "date": "20150205",
        "close": "0.000391",
        "coin": "emerald",
        "open": "0.000410"
    },
    {
        "volume": "3",
        "average": "0.00",
        "high": "0.000579",
        "low": "0.000520",
        "marketcap": "6973",
        "date": "20150205",
        "close": "0.000525",
        "coin": "goldreserve",
        "open": "0.000543"
    },
    {
        "volume": "99",
        "average": "0.00",
        "high": "0.004307",
        "low": "0.002767",
        "marketcap": "4587",
        "date": "20150205",
        "close": "0.002977",
        "coin": "gapcoin",
        "open": "0.002986"
    },
    {
        "volume": "1",
        "average": "0.02",
        "high": "0.019358",
        "low": "0.013667",
        "marketcap": "2546",
        "date": "20150205",
        "close": "0.019310",
        "coin": "litebar",
        "open": "0.014408"
    },
    {
        "volume": "695",
        "average": "225.99",
        "high": "233.21",
        "low": "218.77",
        "marketcap": "13637",
        "date": "20150205",
        "close": "220.91",
        "coin": "bitbtc",
        "open": "232.00"
    },
    {
        "volume": "222",
        "average": "0.01",
        "high": "0.007213",
        "low": "0.005650",
        "marketcap": "25521",
        "date": "20150205",
        "close": "0.005910",
        "coin": "sterlingcoin",
        "open": "0.006599"
    },
    {
        "volume": "1",
        "average": "0.00",
        "high": "0.000206",
        "low": "0.000185",
        "marketcap": "",
        "date": "20150205",
        "close": "0.000187",
        "coin": "tigercoin",
        "open": "0.000195"
    },
    {
        "volume": "8",
        "average": "0.00",
        "high": "0.001740",
        "low": "0.001451",
        "marketcap": "10179",
        "date": "20150205",
        "close": "0.001460",
        "coin": "globalboost-y",
        "open": "0.001652"
    },
    {
        "volume": "71",
        "average": "0.01",
        "high": "0.005700",
        "low": "0.004946",
        "marketcap": "17080",
        "date": "20150205",
        "close": "0.005053",
        "coin": "quatloo",
        "open": "0.005461"
    },
    {
        "volume": "21",
        "average": "0.00",
        "high": "0.002176",
        "low": "0.001954",
        "marketcap": "2959",
        "date": "20150205",
        "close": "0.001964",
        "coin": "argentum",
        "open": "0.002010"
    },
    {
        "volume": "282",
        "average": "0.01",
        "high": "0.013661",
        "low": "0.012687",
        "marketcap": "29460",
        "date": "20150205",
        "close": "0.012698",
        "coin": "securecoin",
        "open": "0.012986"
    },
    {
        "volume": "1",
        "average": "0.00",
        "high": "0.001701",
        "low": "0.001527",
        "marketcap": "2735",
        "date": "20150205",
        "close": "0.001543",
        "coin": "catcoin",
        "open": "0.001609"
    },
    {
        "volume": "14",
        "average": "0.00",
        "high": "0.000239",
        "low": "0.000215",
        "marketcap": "13714",
        "date": "20150205",
        "close": "0.000219",
        "coin": "globalcoin",
        "open": "0.000229"
    },
    {
        "volume": "0",
        "average": "0.00",
        "high": "0.000212",
        "low": "0.000119",
        "marketcap": "",
        "date": "20150205",
        "close": "0.000119",
        "coin": "sativacoin",
        "open": "0.000211"
    },
    {
        "volume": "18",
        "average": "0.12",
        "high": "0.126686",
        "low": "0.110039",
        "marketcap": "3405",
        "date": "20150205",
        "close": "0.112824",
        "coin": "bitgem",
        "open": "0.111434"
    },
    {
        "volume": "4",
        "average": "0.00",
        "high": "0.000436",
        "low": "0.000389",
        "marketcap": "137",
        "date": "20150205",
        "close": "0.000393",
        "coin": "cachecoin",
        "open": "0.000412"
    },
    {
        "volume": "68",
        "average": "0.01",
        "high": "0.006753",
        "low": "0.004859",
        "marketcap": "12394",
        "date": "20150205",
        "close": "0.006618",
        "coin": "philosopher-stones",
        "open": "0.005102"
    },
    {
        "volume": "34",
        "average": "0.01",
        "high": "0.008496",
        "low": "0.007148",
        "marketcap": "4949",
        "date": "20150205",
        "close": "0.007279",
        "coin": "acoin",
        "open": "0.007533"
    },
    {
        "volume": "155",
        "average": "0.00",
        "high": "0.000062",
        "low": "0.000052",
        "marketcap": "54120",
        "date": "20150205",
        "close": "0.000054",
        "coin": "usde",
        "open": "0.000057"
    },
    {
        "volume": "52",
        "average": "0.01",
        "high": "0.011726",
        "low": "0.009594",
        "marketcap": "7827",
        "date": "20150205",
        "close": "0.010903",
        "coin": "goldpieces",
        "open": "0.010274"
    },
    {
        "volume": "2",
        "average": "0.00",
        "high": "0.000139",
        "low": "0.000118",
        "marketcap": "1974",
        "date": "20150205",
        "close": "0.000119",
        "coin": "spots",
        "open": "0.000134"
    },
    {
        "volume": "6",
        "average": "0.00",
        "high": "0.001573",
        "low": "0.001341",
        "marketcap": "2115",
        "date": "20150205",
        "close": "0.001519",
        "coin": "quazarcoin",
        "open": "0.001358"
    },
    {
        "volume": "14",
        "average": "0.02",
        "high": "0.017326",
        "low": "0.014082",
        "marketcap": "4179",
        "date": "20150205",
        "close": "0.014365",
        "coin": "ronpaulcoin",
        "open": "0.016977"
    },
    {
        "volume": "22",
        "average": "0.00",
        "high": "0.000481",
        "low": "0.000434",
        "marketcap": "12893",
        "date": "20150205",
        "close": "0.000437",
        "coin": "yacoin",
        "open": "0.000441"
    },
    {
        "volume": "2038",
        "average": "1270.65",
        "high": "1303.24",
        "low": "1238.06",
        "marketcap": "26434",
        "date": "20150205",
        "close": "1250.16",
        "coin": "bitgold",
        "open": "1301.74"
    },
    {
        "volume": "11",
        "average": "0.00",
        "high": "0.000577",
        "low": "0.000494",
        "marketcap": "2432",
        "date": "20150205",
        "close": "0.000499",
        "coin": "cashcoin",
        "open": "0.000534"
    },
    {
        "volume": "1",
        "average": "0.00",
        "high": "2.9e-07",
        "low": "2.8e-07",
        "marketcap": "1428",
        "date": "20150205",
        "close": "2.8e-07",
        "coin": "photon",
        "open": "2.9e-07"
    },
    {
        "volume": "26",
        "average": "0.00",
        "high": "8.6e-08",
        "low": "6.4e-08",
        "marketcap": "4992",
        "date": "20150205",
        "close": "8.1e-08",
        "coin": "gcoin",
        "open": "7.3e-08"
    },
    {
        "volume": "71",
        "average": "0.00",
        "high": "0.000005",
        "low": "0.000002",
        "marketcap": "44770",
        "date": "20150205",
        "close": "0.000004",
        "coin": "virtacoin",
        "open": "0.000004"
    },
    {
        "volume": "46",
        "average": "0.00",
        "high": "0.000026",
        "low": "0.000019",
        "marketcap": "16540",
        "date": "20150205",
        "close": "0.000020",
        "coin": "incakoin",
        "open": "0.000025"
    },
    {
        "volume": "157",
        "average": "0.01",
        "high": "0.007972",
        "low": "0.006020",
        "marketcap": "44663",
        "date": "20150205",
        "close": "0.006044",
        "coin": "cryptcoin",
        "open": "0.007431"
    },
    {
        "volume": "1369",
        "average": "0.06",
        "high": "0.059597",
        "low": "0.051554",
        "marketcap": "360700",
        "date": "20150205",
        "close": "0.054884",
        "coin": "shadowcash",
        "open": "0.055838"
    },
    {
        "volume": "69",
        "average": "0.00",
        "high": "0.000140",
        "low": "0.000110",
        "marketcap": "48228",
        "date": "20150205",
        "close": "0.000139",
        "coin": "fimkrypto",
        "open": "0.000113"
    },
    {
        "volume": "0",
        "average": "0.00",
        "high": "0.004308",
        "low": "0.003865",
        "marketcap": "7345",
        "date": "20150205",
        "close": "0.003905",
        "coin": "mincoin",
        "open": "0.004267"
    },
    {
        "volume": "11",
        "average": "0.00",
        "high": "8.2e-07",
        "low": "7.3e-07",
        "marketcap": "11182",
        "date": "20150205",
        "close": "7.9e-07",
        "coin": "lottocoin",
        "open": "7.7e-07"
    },
    {
        "volume": "1",
        "average": "0.00",
        "high": "0.000027",
        "low": "0.000022",
        "marketcap": "",
        "date": "20150205",
        "close": "0.000022",
        "coin": "metalcoin",
        "open": "0.000025"
    },
    {
        "volume": "0",
        "average": "0.00",
        "high": "0.000002",
        "low": "0.000002",
        "marketcap": "682",
        "date": "20150205",
        "close": "0.000002",
        "coin": "blazecoin",
        "open": "0.000002"
    },
    {
        "volume": "0",
        "average": "0.00",
        "high": "0.001340",
        "low": "0.001202",
        "marketcap": "",
        "date": "20150205",
        "close": "0.001219",
        "coin": "joincoin",
        "open": "0.001268"
    },
    {
        "volume": "23",
        "average": "0.00",
        "high": "0.001389",
        "low": "0.001251",
        "marketcap": "60354",
        "date": "20150205",
        "close": "0.001264",
        "coin": "freicoin",
        "open": "0.001313"
    },
    {
        "volume": "21",
        "average": "0.00",
        "high": "4.3e-07",
        "low": "3.8e-07",
        "marketcap": "10170",
        "date": "20150205",
        "close": "3.8e-07",
        "coin": "kittehcoin",
        "open": "4.3e-07"
    },
    {
        "volume": "52",
        "average": "0.04",
        "high": "0.042546",
        "low": "0.035755",
        "marketcap": "13145",
        "date": "20150205",
        "close": "0.036766",
        "coin": "franko",
        "open": "0.037556"
    },
    {
        "volume": "1175",
        "average": "0.01",
        "high": "0.011840",
        "low": "0.010740",
        "marketcap": "131135",
        "date": "20150205",
        "close": "0.010774",
        "coin": "boostcoin",
        "open": "0.011179"
    },
    {
        "volume": "3211",
        "average": "0.25",
        "high": "0.276910",
        "low": "0.216595",
        "marketcap": "249645",
        "date": "20150205",
        "close": "0.216595",
        "coin": "uro",
        "open": "0.243590"
    },
    {
        "volume": "0",
        "average": "0.00",
        "high": "0.000264",
        "low": "0.000172",
        "marketcap": "426",
        "date": "20150205",
        "close": "0.000239",
        "coin": "beavercoin",
        "open": "0.000198"
    },
    {
        "volume": "472",
        "average": "0.00",
        "high": "0.000466",
        "low": "0.000162",
        "marketcap": "4207",
        "date": "20150205",
        "close": "0.000434",
        "coin": "plncoin",
        "open": "0.000254"
    },
    {
        "volume": "31",
        "average": "0.00",
        "high": "0.000907",
        "low": "0.000655",
        "marketcap": "100889",
        "date": "20150205",
        "close": "0.000738",
        "coin": "cryptoescudo",
        "open": "0.000907"
    },
    {
        "volume": "46",
        "average": "0.01",
        "high": "0.011004",
        "low": "0.002251",
        "marketcap": "784",
        "date": "20150205",
        "close": "0.007229",
        "coin": "crtcoin",
        "open": "0.009890"
    },
    {
        "volume": "245",
        "average": "0.00",
        "high": "0.000001",
        "low": "9.2e-07",
        "marketcap": "62049",
        "date": "20150205",
        "close": "0.000001",
        "coin": "karmacoin",
        "open": "9.5e-07"
    },
    {
        "volume": "321",
        "average": "0.00",
        "high": "0.000001",
        "low": "0.000001",
        "marketcap": "50313",
        "date": "20150205",
        "close": "0.000001",
        "coin": "htmlcoin",
        "open": "0.000001"
    },
    {
        "volume": "234",
        "average": "0.00",
        "high": "0.000004",
        "low": "0.000004",
        "marketcap": "327734",
        "date": "20150205",
        "close": "0.000004",
        "coin": "infinitecoin",
        "open": "0.000004"
    },
    {
        "volume": "171",
        "average": "0.00",
        "high": "0.000223",
        "low": "0.000138",
        "marketcap": "55257",
        "date": "20150205",
        "close": "0.000163",
        "coin": "vpncoin",
        "open": "0.000138"
    },
    {
        "volume": "2123",
        "average": "0.03",
        "high": "0.047070",
        "low": "0.019679",
        "marketcap": "949589",
        "date": "20150205",
        "close": "0.023867",
        "coin": "storjcoin-x",
        "open": "0.022901"
    },
    {
        "volume": "23",
        "average": "0.00",
        "high": "0.000026",
        "low": "0.000021",
        "marketcap": "8993",
        "date": "20150205",
        "close": "0.000024",
        "coin": "shacoin",
        "open": "0.000025"
    },
    {
        "volume": "1",
        "average": "0.00",
        "high": "0.000067",
        "low": "0.000060",
        "marketcap": "",
        "date": "20150205",
        "close": "0.000061",
        "coin": "skeincoin",
        "open": "0.000067"
    },
    {
        "volume": "0",
        "average": "0.00",
        "high": "0.000009",
        "low": "0.000006",
        "marketcap": "42",
        "date": "20150205",
        "close": "0.000009",
        "coin": "donationcoin",
        "open": "0.000009"
    },
    {
        "volume": "1613",
        "average": "0.00",
        "high": "8.7e-07",
        "low": "1.6e-07",
        "marketcap": "32599",
        "date": "20150205",
        "close": "5.9e-07",
        "coin": "flappycoin",
        "open": "4.7e-07"
    },
    {
        "volume": "0",
        "average": "0.00",
        "high": "0.000096",
        "low": "0.000028",
        "marketcap": "1081",
        "date": "20150205",
        "close": "0.000087",
        "coin": "granitecoin",
        "open": "0.000091"
    },
    {
        "volume": "1",
        "average": "0.00",
        "high": "0.000053",
        "low": "0.000045",
        "marketcap": "4408",
        "date": "20150205",
        "close": "0.000046",
        "coin": "fireflycoin",
        "open": "0.000048"
    },
    {
        "volume": "0",
        "average": "0.01",
        "high": "0.007093",
        "low": "0.004572",
        "marketcap": "2085",
        "date": "20150205",
        "close": "0.006431",
        "coin": "elacoin",
        "open": "0.004572"
    },
    {
        "volume": "158",
        "average": "0.06",
        "high": "0.068228",
        "low": "0.057976",
        "marketcap": "234227",
        "date": "20150205",
        "close": "0.059666",
        "coin": "hyper",
        "open": "0.061117"
    },
    {
        "volume": "5",
        "average": "0.00",
        "high": "0.000244",
        "low": "0.000219",
        "marketcap": "4529",
        "date": "20150205",
        "close": "0.000226",
        "coin": "betacoin",
        "open": "0.000226"
    },
    {
        "volume": "624",
        "average": "0.00",
        "high": "0.000014",
        "low": "0.000011",
        "marketcap": "113180",
        "date": "20150205",
        "close": "0.000013",
        "coin": "qora",
        "open": "0.000011"
    },
    {
        "volume": "13",
        "average": "0.00",
        "high": "0.002446",
        "low": "0.001088",
        "marketcap": "12469",
        "date": "20150205",
        "close": "0.001655",
        "coin": "quotient",
        "open": "0.001469"
    },
    {
        "volume": "3",
        "average": "0.00",
        "high": "0.000023",
        "low": "0.000016",
        "marketcap": "9714",
        "date": "20150205",
        "close": "0.000016",
        "coin": "gameleaguecoin",
        "open": "0.000019"
    },
    {
        "volume": "32",
        "average": "0.00",
        "high": "1.8e-07",
        "low": "1.4e-07",
        "marketcap": "1047",
        "date": "20150205",
        "close": "1.4e-07",
        "coin": "batcoin",
        "open": "1.6e-07"
    },
    {
        "volume": "4",
        "average": "0.00",
        "high": "1.4e-07",
        "low": "1.2e-07",
        "marketcap": "12653",
        "date": "20150205",
        "close": "1.4e-07",
        "coin": "rabbitcoin",
        "open": "1.3e-07"
    },
    {
        "volume": "21",
        "average": "0.00",
        "high": "0.000804",
        "low": "0.000732",
        "marketcap": "24758",
        "date": "20150205",
        "close": "0.000749",
        "coin": "casinocoin",
        "open": "0.000804"
    }
]