[
    {
        "volume": "18453700",
        "average": "853.75",
        "high": "870.15",
        "low": "837.36",
        "marketcap": "10661400000",
        "date": "20140122",
        "close": "845.59",
        "coin": "bitcoin",
        "open": "867.21"
    },
    {
        "volume": "60703",
        "average": "0.02",
        "high": "0.020020",
        "low": "0.019227",
        "marketcap": "156246000",
        "date": "20140122",
        "close": "0.019389",
        "coin": "ripple",
        "open": "0.019986"
    },
    {
        "volume": "10957200",
        "average": "24.02",
        "high": "24.89",
        "low": "23.16",
        "marketcap": "622754000",
        "date": "20140122",
        "close": "23.65",
        "coin": "litecoin",
        "open": "24.85"
    },
    {
        "volume": "5896280",
        "average": "0.00",
        "high": "0.002038",
        "low": "0.001365",
        "marketcap": "65907400",
        "date": "20140122",
        "close": "0.001497",
        "coin": "dogecoin",
        "open": "0.001977"
    },
    {
        "volume": "779705",
        "average": "0.08",
        "high": "0.097685",
        "low": "0.059908",
        "marketcap": "95888100",
        "date": "20140122",
        "close": "0.073608",
        "coin": "nxt",
        "open": "0.095888"
    },
    {
        "volume": "21147",
        "average": "0.27",
        "high": "0.323996",
        "low": "0.223217",
        "marketcap": "281910",
        "date": "20140122",
        "close": "0.241453",
        "coin": "vertcoin",
        "open": "0.276640"
    },
    {
        "volume": "1385800",
        "average": "5.50",
        "high": "5.77",
        "low": "5.23",
        "marketcap": "121507000",
        "date": "20140122",
        "close": "5.40",
        "coin": "peercoin",
        "open": "5.77"
    },
    {
        "volume": "6709",
        "average": "0.00",
        "high": "0.000040",
        "low": "0.000030",
        "marketcap": "837440",
        "date": "20140122",
        "close": "0.000039",
        "coin": "mooncoin",
        "open": "0.000039"
    },
    {
        "volume": "220759",
        "average": "0.31",
        "high": "0.327275",
        "low": "0.301450",
        "marketcap": "9821370",
        "date": "20140122",
        "close": "0.304412",
        "coin": "feathercoin",
        "open": "0.320868"
    },
    {
        "volume": "929264",
        "average": "5.86",
        "high": "6.06",
        "low": "5.65",
        "marketcap": "47237200",
        "date": "20140122",
        "close": "5.77",
        "coin": "namecoin",
        "open": "6.04"
    },
    {
        "volume": "5335",
        "average": "0.00",
        "high": "0.000002",
        "low": "0.000001",
        "marketcap": "143348",
        "date": "20140122",
        "close": "0.000002",
        "coin": "dimecoin",
        "open": "0.000002"
    },
    {
        "volume": "3502",
        "average": "0.73",
        "high": "0.863491",
        "low": "0.599461",
        "marketcap": "139750",
        "date": "20140122",
        "close": "0.721077",
        "coin": "diamond",
        "open": "0.607012"
    },
    {
        "volume": "37096",
        "average": "131.82",
        "high": "139.70",
        "low": "123.95",
        "marketcap": "86388100",
        "date": "20140122",
        "close": "126.09",
        "coin": "omni",
        "open": "139.45"
    },
    {
        "volume": "198042",
        "average": "0.00",
        "high": "0.001750",
        "low": "0.001376",
        "marketcap": "1571180",
        "date": "20140122",
        "close": "0.001640",
        "coin": "earthcoin",
        "open": "0.001717"
    },
    {
        "volume": "19357",
        "average": "0.00",
        "high": "0.000002",
        "low": "9.5e-07",
        "marketcap": "127405",
        "date": "20140122",
        "close": "0.000002",
        "coin": "fedoracoin",
        "open": "0.000001"
    },
    {
        "volume": "4266",
        "average": "0.01",
        "high": "0.016720",
        "low": "0.011116",
        "marketcap": "558627",
        "date": "20140122",
        "close": "0.012208",
        "coin": "florincoin",
        "open": "0.014146"
    },
    {
        "volume": "217350",
        "average": "2.98",
        "high": "3.10",
        "low": "2.85",
        "marketcap": "12672500",
        "date": "20140122",
        "close": "2.88",
        "coin": "primecoin",
        "open": "3.08"
    },
    {
        "volume": "8337",
        "average": "4.29",
        "high": "5.03",
        "low": "3.56",
        "marketcap": "533128",
        "date": "20140122",
        "close": "3.71",
        "coin": "unobtanium",
        "open": "3.99"
    },
    {
        "volume": "12212",
        "average": "0.04",
        "high": "0.049556",
        "low": "0.033992",
        "marketcap": "1326200",
        "date": "20140122",
        "close": "0.038162",
        "coin": "goldcoin",
        "open": "0.045078"
    },
    {
        "volume": "17055",
        "average": "0.01",
        "high": "0.015948",
        "low": "0.010980",
        "marketcap": "670491",
        "date": "20140122",
        "close": "0.012184",
        "coin": "sexcoin",
        "open": "0.012097"
    },
    {
        "volume": "40372",
        "average": "14.30",
        "high": "14.64",
        "low": "13.97",
        "marketcap": "8241950",
        "date": "20140122",
        "close": "13.99",
        "coin": "novacoin",
        "open": "14.49"
    },
    {
        "volume": "94797",
        "average": "0.09",
        "high": "0.092168",
        "low": "0.084834",
        "marketcap": "21200800",
        "date": "20140122",
        "close": "0.087941",
        "coin": "quark",
        "open": "0.085715"
    },
    {
        "volume": "853",
        "average": "0.12",
        "high": "0.122937",
        "low": "0.110781",
        "marketcap": "2046200",
        "date": "20140122",
        "close": "0.120776",
        "coin": "ixcoin",
        "open": "0.115139"
    },
    {
        "volume": "18421",
        "average": "0.38",
        "high": "0.398585",
        "low": "0.368685",
        "marketcap": "1941980",
        "date": "20140122",
        "close": "0.372060",
        "coin": "terracoin",
        "open": "0.390245"
    },
    {
        "volume": "12105",
        "average": "3.72",
        "high": "4.08",
        "low": "3.36",
        "marketcap": "2647270",
        "date": "20140122",
        "close": "3.66",
        "coin": "anoncoin",
        "open": "3.90"
    },
    {
        "volume": "312557",
        "average": "0.37",
        "high": "0.399764",
        "low": "0.331917",
        "marketcap": "14931200",
        "date": "20140122",
        "close": "0.354488",
        "coin": "worldcoin",
        "open": "0.362537"
    },
    {
        "volume": "23643",
        "average": "0.01",
        "high": "0.014596",
        "low": "0.013159",
        "marketcap": "2796930",
        "date": "20140122",
        "close": "0.014062",
        "coin": "netcoin",
        "open": "0.013459"
    },
    {
        "volume": "19990",
        "average": "1.05",
        "high": "1.18",
        "low": "0.916243",
        "marketcap": "881273",
        "date": "20140122",
        "close": "1.18",
        "coin": "cryptogenic-bullion",
        "open": "0.940923"
    },
    {
        "volume": "29483",
        "average": "0.01",
        "high": "0.016107",
        "low": "0.011485",
        "marketcap": "627128",
        "date": "20140122",
        "close": "0.014384",
        "coin": "fastcoin",
        "open": "0.011716"
    },
    {
        "volume": "51706",
        "average": "0.69",
        "high": "0.796577",
        "low": "0.586552",
        "marketcap": "13606000",
        "date": "20140122",
        "close": "0.788555",
        "coin": "megacoin",
        "open": "0.623342"
    },
    {
        "volume": "7428",
        "average": "0.02",
        "high": "0.025156",
        "low": "0.020886",
        "marketcap": "3792450",
        "date": "20140122",
        "close": "0.022831",
        "coin": "zetacoin",
        "open": "0.023735"
    },
    {
        "volume": "34362",
        "average": "0.28",
        "high": "0.299508",
        "low": "0.269630",
        "marketcap": "3662180",
        "date": "20140122",
        "close": "0.279104",
        "coin": "digitalcoin",
        "open": "0.292371"
    },
    {
        "volume": "596",
        "average": "0.05",
        "high": "0.051940",
        "low": "0.046833",
        "marketcap": "133788",
        "date": "20140122",
        "close": "0.048199",
        "coin": "hobonickels",
        "open": "0.050620"
    },
    {
        "volume": "957",
        "average": "0.03",
        "high": "0.027920",
        "low": "0.023717",
        "marketcap": "542969",
        "date": "20140122",
        "close": "0.023846",
        "coin": "i0coin",
        "open": "0.026979"
    },
    {
        "volume": "5130",
        "average": "0.09",
        "high": "0.099124",
        "low": "0.071499",
        "marketcap": "295425",
        "date": "20140122",
        "close": "0.089083",
        "coin": "deutsche-emark",
        "open": "0.080676"
    },
    {
        "volume": "55255",
        "average": "345252.00",
        "high": "403444",
        "low": "287060",
        "marketcap": "293072",
        "date": "20140122",
        "close": "334008",
        "coin": "42-coin",
        "open": "287133"
    },
    {
        "volume": "14003",
        "average": "79.25",
        "high": "88.02",
        "low": "70.48",
        "marketcap": "736657",
        "date": "20140122",
        "close": "79.95",
        "coin": "bitbar",
        "open": "79.21"
    },
    {
        "volume": "3431",
        "average": "0.01",
        "high": "0.014675",
        "low": "0.012106",
        "marketcap": "128118",
        "date": "20140122",
        "close": "0.014164",
        "coin": "phoenixcoin",
        "open": "0.014647"
    },
    {
        "volume": "3041",
        "average": "0.02",
        "high": "0.024176",
        "low": "0.018588",
        "marketcap": "87126",
        "date": "20140122",
        "close": "0.023465",
        "coin": "joulecoin",
        "open": "0.024082"
    },
    {
        "volume": "6179",
        "average": "1.35",
        "high": "1.43",
        "low": "1.28",
        "marketcap": "967875",
        "date": "20140122",
        "close": "1.29",
        "coin": "tagcoin",
        "open": "1.32"
    },
    {
        "volume": "19917",
        "average": "0.01",
        "high": "0.019600",
        "low": "0.005792",
        "marketcap": "147748",
        "date": "20140122",
        "close": "0.010257",
        "coin": "tigercoin",
        "open": "0.005819"
    },
    {
        "volume": "4593",
        "average": "0.21",
        "high": "0.254651",
        "low": "0.173803",
        "marketcap": "152004",
        "date": "20140122",
        "close": "0.204684",
        "coin": "argentum",
        "open": "0.238543"
    },
    {
        "volume": "338965",
        "average": "0.77",
        "high": "1.21",
        "low": "0.320271",
        "marketcap": "366431",
        "date": "20140122",
        "close": "0.761023",
        "coin": "catcoin",
        "open": "0.346884"
    },
    {
        "volume": "2759",
        "average": "0.01",
        "high": "0.008899",
        "low": "0.007214",
        "marketcap": "232169",
        "date": "20140122",
        "close": "0.007771",
        "coin": "globalcoin",
        "open": "0.008811"
    },
    {
        "volume": "1176",
        "average": "0.16",
        "high": "0.172856",
        "low": "0.147629",
        "marketcap": "275774",
        "date": "20140122",
        "close": "0.159698",
        "coin": "philosopher-stones",
        "open": "0.166886"
    },
    {
        "volume": "7042",
        "average": "13.72",
        "high": "14.76",
        "low": "12.68",
        "marketcap": "198895",
        "date": "20140122",
        "close": "14.20",
        "coin": "ronpaulcoin",
        "open": "14.76"
    },
    {
        "volume": "1678",
        "average": "0.03",
        "high": "0.033738",
        "low": "0.025069",
        "marketcap": "378156",
        "date": "20140122",
        "close": "0.028750",
        "coin": "yacoin",
        "open": "0.025149"
    },
    {
        "volume": "5170",
        "average": "0.62",
        "high": "0.688170",
        "low": "0.551669",
        "marketcap": "906635",
        "date": "20140122",
        "close": "0.621007",
        "coin": "mincoin",
        "open": "0.592406"
    },
    {
        "volume": "1106390",
        "average": "0.00",
        "high": "0.000596",
        "low": "0.000338",
        "marketcap": "1905650",
        "date": "20140122",
        "close": "0.000406",
        "coin": "lottocoin",
        "open": "0.000408"
    },
    {
        "volume": "1141",
        "average": "0.06",
        "high": "0.060733",
        "low": "0.050537",
        "marketcap": "1971070",
        "date": "20140122",
        "close": "0.052367",
        "coin": "freicoin",
        "open": "0.054634"
    },
    {
        "volume": "649",
        "average": "1.58",
        "high": "1.63",
        "low": "1.54",
        "marketcap": "160269",
        "date": "20140122",
        "close": "1.58",
        "coin": "franko",
        "open": "1.63"
    },
    {
        "volume": "81694",
        "average": "0.00",
        "high": "0.000096",
        "low": "0.000063",
        "marketcap": "5729410",
        "date": "20140122",
        "close": "0.000085",
        "coin": "infinitecoin",
        "open": "0.000064"
    },
    {
        "volume": "5392",
        "average": "0.94",
        "high": "1.12",
        "low": "0.753434",
        "marketcap": "156086",
        "date": "20140122",
        "close": "0.955610",
        "coin": "elacoin",
        "open": "0.867210"
    },
    {
        "volume": "387",
        "average": "0.03",
        "high": "0.040557",
        "low": "0.024215",
        "marketcap": "139175",
        "date": "20140122",
        "close": "0.035109",
        "coin": "betacoin",
        "open": "0.024282"
    },
    {
        "volume": "11617",
        "average": "0.02",
        "high": "0.023592",
        "low": "0.013866",
        "marketcap": "132776",
        "date": "20140122",
        "close": "0.017901",
        "coin": "casinocoin",
        "open": "0.013893"
    }
]